Workbook

Sheet 1. Overview & Per-Week Summary
A1: AI AUDIT LOG - CONSOLIDATED SUMMARY (WEEK 1 - WEEK 11)
A2: Tổng hợp toàn bộ 11 file AI Audit Log hàng tuần thành một báo cáo duy nhất cho toàn dự án.
A4: STUDENT INFORMATION
A5: Student Name: | C5: Trần Tiến Hùng
A6: Student ID: | C6: DE190119
A7: Course: | C7: SWP391
A8: Project: | C8: Dermatology Clinic Management System
A10: PROJECT-WIDE AI USAGE SUMMARY
A11: Total Prompts Used (Week 1-11, all AI tools): | C11: =C29 -> 585
A12: Total Core Prompts Logged (Week 1-11): | C12: =D29 -> 81
A13: Overall Selection Ratio: | C13: =C12/C11 -> 0.13846154
A14: Total Hallucinations Detected (Week 1-11): | C14: =F29 -> 34
A16: PER-WEEK BREAKDOWN
A17: Week | B17: Assignment / Trọng tâm tuần | C17: Total Prompts | D17: Core Prompts | E17: Selection Ratio | F17: Hallucination Detected
A18: Week 1 | B18: Project - Dermatology Clinic Management System | C18: 50 | D18: 10 | E18: =D18/C18 -> 0.2 | F18: 3
A19: Week 2 | B19: Project - Dermatology Clinic Management System (Database Design & Authentication Phase) | C19: 58 | D19: 11 | E19: =D19/C19 -> 0.18965517 | F19: 3
A20: Week 3 | B20: Project - Dermatology Clinic Management System (Logic Flows & Dashboards) | C20: 30 | D20: 6 | E20: =D20/C20 -> 0.2 | F20: 3
A21: Week 4 | B21: Project - Dermatology Clinic Management System (Doctor Workflow & DB Integration) | C21: 42 | D21: 6 | E21: =D21/C21 -> 0.14285714 | F21: 3
A22: Week 5 | B22: Project - Dermatology Clinic Management System (UI Refinements & Staff Workflows) | C22: 60 | D22: 7 | E22: =D22/C22 -> 0.11666667 | F22: 3
A23: Week 6 | B23: Project - Dermatology Clinic Management System (Receptionist Flow & UI Polish) | C23: 48 | D23: 6 | E23: =D23/C23 -> 0.125 | F23: 3
A24: Week 7 | B24: Project - Dermatology Clinic Management System (Admin Refactor & Multi-role Workflows) | C24: 58 | D24: 6 | E24: =D24/C24 -> 0.10344828 | F24: 3
A25: Week 8 | B25: Project - Dermatology Clinic Management System (Doctor & Technician UI Polish - Liquid Glass Effects, Icon System Revamp, Voucher Bug Fix) | C25: 42 | D25: 6 | E25: =D25/C25 -> 0.14285714 | F25: 3
A26: Week 9 | B26: Project - Dermatology Clinic Management System (AI Scanner, Chatbot & Scheduling) | C26: 67 | D26: 7 | E26: =D26/C26 -> 0.10447761 | F26: 3
A27: Week 10 | B27: Project - Dermatology Clinic Management System (AI Skin Scan Fix, Chatbot-Receptionist Integration, Voice-to-Form AI, Messaging & Calendar UI Overhaul, Performance Optimization) | C27: 80 | D27: 9 | E27: =D27/C27 -> 0.1125 | F27: 4
A28: Week 11 | B28: Project - Dermatology Clinic Management System (Mid-Project Audit & Regression Review - Weeks 1-10) | C28: 50 | D28: 7 | E28: =D28/C28 -> 0.14 | F28: 3
A29: TOTAL | C29: =SUM(C18:C28) -> 585 | D29: =SUM(D18:D28) -> 81 | E29: =D29/C29 -> 0.13846154 | F29: =SUM(F18:F28) -> 34
A30: Ghi chú: Số Total Prompts của Week 1 trong file gốc ghi là "~50" (giá trị gần đúng do sinh viên tự ước lượng); đã quy đổi thành 50 để phục vụ tính tổng toàn dự án.
A32: AI TOOLS USED ACROSS THE PROJECT
A33: AI Tool | B33: Vai trò xuyên suốt dự án (Week 1-11)
A34: Claude (on Antigravity) | B34: Công cụ chính xuyên suốt cả dự án: vibe coding toàn bộ chức năng, giao diện và logic nghiệp vụ - từ thiết kế DB/Auth (Week 1-2), luồng nghiệp vụ đa vai trò (Week 3-7), các tính năng AI (Skin Scanner, Chatbot, Voice-to-Form - Week 9-10), đến rà soát/refactor trong tuần audit (Week 11). | F34: High (11/11 tuần)
A35: ChatGPT | B35: Vai trò linh hoạt theo từng giai đoạn: kiểm tra cú pháp và test luồng ở giai đoạn đầu (Week 1-7), đánh giá hậu kiểm sau khi Claude code xong ở giai đoạn tính năng AI (Week 9-10), và soạn kịch bản regression/load test trong tuần audit (Week 11). | F35: High/Medium (11/11 tuần)
A36: Gemini | B36: Vai trò linh hoạt theo từng giai đoạn: gợi ý kiến trúc và giải đáp bảo mật ở giai đoạn đầu-giữa (Week 1-9), tinh chỉnh prompt hoàn chỉnh (Prompt Engineering) cho Claude ở Week 10, và phân tích tính nhất quán kiến trúc toàn dự án ở tuần audit (Week 11). | F36: Medium/High (11/11 tuần)
A38: DTC COMPONENT DISTRIBUTION - WHOLE PROJECT
A39: DTC Component | B39: Total Core Prompts (Week 1-11) | C39: Required (Min)
A40: Decomposition | B40: =COUNTIF('2. Detailed Audit Log'!D:D,A40) -> 24 | C40: >= 1 per week (11 weeks)
A41: Pattern Recognition | B41: =COUNTIF('2. Detailed Audit Log'!D:D,A41) -> 24 | C41: >= 1 per week (11 weeks)
A42: Abstraction | B42: =COUNTIF('2. Detailed Audit Log'!D:D,A42) -> 18 | C42: >= 1 per week (11 weeks)
A43: Algorithms | B43: =COUNTIF('2. Detailed Audit Log'!D:D,A43) -> 15 | C43: >= 1 per week (11 weeks)

Sheet 2. Detailed Audit Log
A1: DETAILED AI AUDIT LOG - ALL WEEKS (1-11)
A2: Tổng hợp toàn bộ CORE PROMPTS (Decision/Problem-Solving/Verification) từ 11 tuần. Mỗi entry giữ nguyên số thứ tự gốc trong tuần (Entry #) và được gắn thêm cột Week để tra cứu.
A3: Week | B3: Entry # | C3: Prompt Type | D3: Stage/Component | E3: Problem/Context | F3: Prompt to AI | G3: AI Response (Summary) | H3: Human Delta & Reflection | I3: Evidence
A4: Week 1 | B4: 001 | C4: DECISION | D4: Decomposition | E4: Cần chia nhỏ hệ thống phòng khám thành các module | F4: I am building a Dermatology Clinic Management System for my SWP391 project. Suggest the core modules I need to build. | G4: AI gợi ý 12 modules bao gồm: Patient, Doctor, Appointment, AI Analysis, Billing, Pharmacy, HR, Marketing, Inventory, Analytics, Payroll, CRM. | H4: Critical Thinking: 12 modules là quá đồ sộ so với quy mô nhóm 5 người trong 1 kỳ học. Contextualization: Giới hạn dự án SWP391 chỉ tập trung vào luồng nghiệp vụ cốt lõi. Creative Synthesis: Tôi đã gộp và cắt giảm xuống còn 5 modules chính: User Auth, Appointment, Medical Record (kèm AI soi da), Billing, Pharmacy. Decision: Chốt thiết kế kiến trúc với 5 modules cốt lõi để đảm bảo đúng tiến độ. | I4: UML Package Diagram
A5: Week 1 | B5: 002 | C5: DECISION | D5: Decomposition | E5: Thiết kế luồng phân tích ảnh AI soi da | F5: How should I divide the workflow for the AI skin analysis feature in my clinic system? | G5: AI gợi ý: Bệnh nhân upload ảnh -> Server xử lý qua AI -> Trả kết quả thẳng cho bệnh nhân để tự xem xét. | H5: Critical Thinking: Việc trả kết quả AI trực tiếp cho bệnh nhân mà không qua bác sĩ có rủi ro lớn về y tế và tâm lý. Contextualization: Đây là hệ thống quản lý y tế chính thống, AI chỉ mang tính 'hỗ trợ' (assistive), quyết định cuối cùng phải là con người. Creative Synthesis: Tôi đổi lại luồng hoạt động: Bệnh nhân upload -> AI phân tích -> Kết quả lưu vào dạng bản nháp (draft) -> Bác sĩ review và chốt chẩn đoán -> Bệnh nhân mới được xem. Decision: Áp dụng mô hình luồng Human-in-the-loop. | I5: Activity Diagram
A6: Week 1 | B6: 003 | C6: PROBLEM-SOLVING | D6: Decomposition | E6: Tách logic và cấu trúc thanh toán hóa đơn | F6: The Billing module is getting complex with clinic fee, medicine fee, and AI service fee. How to decompose it? | G6: AI khuyên dùng Invoice Service riêng biệt, tách rời hoàn toàn các bảng cơ sở dữ liệu Clinic_Fee, Medicine_Fee, Service_Fee. | H6: Critical Thinking: Thiết kế quá rời rạc như vậy sẽ dẫn đến việc hệ thống phải thực hiện nhiều phép join bảng phức tạp khi truy vấn hóa đơn. Contextualization: Hệ thống cơ sở dữ liệu cần tối ưu hóa hiệu năng truy vấn cho hóa đơn tổng của một ca khám bệnh. Creative Synthesis: Tôi gom thành 1 bảng Invoice duy nhất để quản lý chung, có bảng phụ Invoice_Details lưu phân loại (type) của từng item. Decision: Gom nhóm DB hợp lý để giảm độ phức tạp cho luồng code backend. | I6: ERD Diagram v1
A7: Week 1 | B7: 004 | C7: DECISION | D7: Pattern Recognition | E7: Quản lý hệ thống phân quyền (RBAC) cho nhiều role | F7: I have 4 roles: Admin, Doctor, Receptionist, Technician. How to structure their permissions efficiently? | G7: AI gợi ý tạo 4 bảng dữ liệu người dùng riêng biệt hoàn toàn: Admin_Table, Doctor_Table, Receptionist_Table, Technician_Table để quản lý độc lập. | H7: Critical Thinking: Việc tạo nhiều bảng user riêng lẻ sẽ gây trùng lặp mã nguồn (vi phạm nguyên lý DRY) khi làm chức năng Login/Forgot Password. Contextualization: Tất cả các phân hệ phân quyền và role trong dự án y tế này đều sử dụng chung một cơ chế xác thực. Creative Synthesis: Tôi nhận diện được pattern chung này và gom về 1 bảng Account duy nhất, sử dụng trường RoleID làm khóa ngoại để phân quyền. Decision: Sử dụng mô hình RBAC chuẩn hóa với 1 bảng Account tập trung. | I7: Class Diagram
A8: Week 1 | B8: 005 | C8: DECISION | D8: Pattern Recognition | E8: Thiết kế mẫu giao diện Dashboard cho các vai trò | F8: What is a good UI pattern for medical dashboards with different roles? | G8: AI khuyên làm 1 trang Dashboard động hoàn toàn, load và render các component trực tiếp dựa vào role hiện tại của tài liệu session. | H8: Critical Thinking: Thiết kế UI động quá phức tạp cho năng lực của team frontend tại thời điểm hiện tại, dễ gây ra lỗ hổng bảo mật render. Contextualization: Dự án cần sự ổn định và phân tách rõ ràng giao diện của từng bộ phận. Creative Synthesis: Tôi tách thành các layout tĩnh riêng biệt (DoctorLayout, AdminLayout) kế thừa chung từ 1 BaseLayout cố định. Decision: Áp dụng Pattern giao diện cấu trúc để dễ dàng lập trình frontend. | I8: UI Wireframe
A9: Week 1 | B9: 006 | C9: DECISION | D9: Abstraction | E9: Trừu tượng hóa và thiết kế thực thể Hồ sơ y tế | F9: Help me design the Class Diagram for MedicalRecord and Prescription in a dermatology context. | G9: AI thiết kế Prescription (Đơn thuốc) là 1 thuộc tính kiểu String nằm trực tiếp ngay bên trong bảng MedicalRecord. | H9: Critical Thinking: Đơn thuốc thực tế bao gồm rất nhiều loại thuốc, số lượng, liều dùng chi tiết, không thể gói gọn trong một chuỗi String. Contextualization: Hệ thống cần quản lý, truy xuất chi tiết từng viên thuốc và đồng bộ với kho thuốc sau này. Creative Synthesis: Trừu tượng hóa thực thể: Tách Prescription thành một Class riêng biệt (quan hệ 1-1 với MedicalRecord), và thêm Class PrescriptionDetail (quan hệ 1-N). Decision: Thiết kế quan hệ thực thể chuẩn hóa để đảm bảo nghiệp vụ đơn thuốc điện tử. | I9: ERD - Record
A10: Week 1 | B10: 007 | C10: DECISION | D10: Abstraction | E10: Mô hình hóa Use Case Đặt lịch khám trực tuyến | F10: What are the actors and use cases for 'Book Appointment'? | G10: AI liệt kê Actor duy nhất: Patient. Các use cases đi kèm: View Schedule, Select Doctor, Pay deposit. | H10: Critical Thinking: AI đã bỏ quên một trường hợp thực tế là Receptionist (Lễ tân) - người có thẩm quyền đặt lịch trực tiếp thay cho bệnh nhân gọi qua điện thoại. Contextualization: Quy trình vận hành phòng khám thực tế luôn yêu cầu sự đồng bộ giữa đặt lịch online và offline. Creative Synthesis: Thêm Actor Receptionist vào sơ đồ, liên kết thiết kế dùng chung Use Case 'Book Appointment' với Patient. Decision: Cập nhật sơ đồ Use Case tổng thể của hệ thống. | I10: Use Case Diagram
A11: Week 1 | B11: 008 | C11: PROBLEM-SOLVING | D11: Abstraction | E11: Giải pháp lưu trữ tệp hình ảnh soi da của AI | F11: How should I store the AI skin scan result images in the database? | G11: AI khuyên lưu trực tiếp tệp hình ảnh dưới dạng dữ liệu nhị phân BLOB ngay trong MySQL database. | H11: Critical Thinking: Lưu ảnh bằng BLOB sẽ làm phình to dung lượng DB cực kỳ nhanh, kéo tụt hiệu năng query và backup dữ liệu. Contextualization: Ảnh y tế soi da thường có độ phân giải cao và số lượng lưu trữ rất lớn. Creative Synthesis: Trừu tượng hóa lớp lưu trữ: Cơ sở dữ liệu chỉ lưu chuỗi Image_URL. Tệp ảnh vật lý sẽ được đẩy lên Cloudinary. Decision: Lưu URL vào CSDL, lưu file gốc trên nền tảng Cloud. | I11: DB Schema
A12: Week 1 | B12: 009 | C12: PROBLEM-SOLVING | D12: Algorithms | E12: Thuật toán kiểm tra trùng lịch hẹn (Scheduling) | F12: If a user books an appointment at 9:00 AM, how to prevent overlapping with others? | G12: AI viết thuật toán kiểm tra trùng lịch đơn giản bằng cách so khớp chính xác: `WHERE Appointment_Time = New_Time`. | H12: Critical Thinking: Cách check so khớp chính xác này sai hoàn toàn về mặt logic toán học, vì mỗi ca khám đều có một khoảng thời gian (Duration). Contextualization: Các ca dịch vụ tiểu phẫu da liễu có thời gian kéo dài khác nhau (15 phút, 30 phút, 1 tiếng). Creative Synthesis: Viết lại thuật toán dựa trên logic kiểm tra khoảng thời gian giao nhau: `New_Start < Exist_End` AND `New_End > Exist_Start`. Decision: Áp dụng thuật toán Interval Overlap check để kiểm soát lịch hẹn chính xác. | I12: Code Snippet
A13: Week 1 | B13: 010 | C13: DECISION | D13: Algorithms | E13: Điều phối hàng chờ khám tại phòng khám (Waiting Queue) | F13: How to manage the patient queue in the clinic on the actual day? | G13: AI gợi ý sử dụng thuật toán hàng đợi cơ bản FIFO (First In, First Out) bằng cấu trúc dữ liệu Queue. | H13: Critical Thinking: Cơ chế FIFO thuần túy không đáp ứng được các tình huống thực tế như bệnh nhân cấp cứu hoặc người đã đặt lịch hẹn trước đúng giờ. Contextualization: Phòng khám cần ưu tiên cao nhất cho người đã đặt lịch qua ứng dụng để tăng trải nghiệm. Creative Synthesis: Chuyển đổi sang thuật toán Priority Queue (Hàng đợi ưu tiên). Trọng số ưu tiên: Cấp cứu > Đặt lịch đúng giờ > Khách vãng lai. Decision: Triển khai cấu trúc Priority Queue cho module điều phối hàng chờ tại quầy. | I13: Logic Flowchart
A14: Week 2 | B14: 001 | C14: DECISION | D14: Decomposition | E14: Chia nhỏ luồng Đăng ký tài khoản thành các bước xử lý dữ liệu và kiểm tra (validation) rõ ràng để phân công cho team. | F14: Break down the User Registration workflow for a clinic system into frontend validation, backend processing, and database persistence steps. | G14: Gemini gợi ý luồng 7 bước đầy đủ: (1) FE validate form → (2) POST /register → (3) BE kiểm tra email trùng → (4) BCrypt hash password → (5) Lưu DB status='PENDING' → (6) Tạo OTP 6 số → (7) Gửi OTP qua email SMTP để kích hoạt tài khoản. | H14: Critical Thinking: Luồng 7 bước hoàn chỉnh về bảo mật, nhưng tích hợp SMTP ngay từ đầu sẽ làm team mắc kẹt ở config dịch vụ email bên ngoài thay vì hoàn thiện core flow. Contextualization: Giai đoạn Sprint 1 mục tiêu là thông luồng chức năng chính. SMTP là dependency ngoài có thể gây chặn tiến độ nếu cấu hình sai. Creative Synthesis: Tách luồng thành 2 phase — Phase A (core flow: Register→Hash→Save→Auto-activate cho dev), Phase B (tích hợp SMTP OTP ở sprint sau). DB và API vẫn thiết kế đủ cột OTP để tích hợp sau. Decision: Implement đủ 7 bước ở tầng BE+DB (bảng OTP_Tokens, API /verify-otp), nhưng ở môi trường dev OTP trả về response JSON để test nhanh. SMTP tích hợp ở sprint tiếp theo. | I14: Sơ đồ luồng đăng ký (draw.io); API endpoint list /register /verify-otp
... A84: Week 11 | B84: 007 | C84: DECISION | D84: Decomposition | E84: Phân rã báo cáo audit tổng kết thành roadmap khắc phục nợ kỹ thuật được sắp xếp theo mức độ ưu tiên cho các tuần tiếp theo | F84: Based on everything found during this audit week (missing @PreAuthorize, duplicated atomic-update logic, retrofit needed for Admin Liquid Glass/AppIcon, voice-to-form race condition), help me decompose all these findings into a structured remediation roadmap I can present in my audit report. | G84: Claude liệt kê tất cả các phát hiện thành một danh sách duy nhất xếp theo đúng thứ tự phát hiện (tức theo thứ tự Entry 001 đến 006), không phân theo mức độ nghiêm trọng hay effort cần thiết. | H84: Critical Thinking: Xếp theo thứ tự phát hiện thay vì theo mức độ nghiêm trọng khiến báo cáo audit trông lộn xộn — lỗ hổng bảo mật RBAC (Entry 004, nghiêm trọng, effort thấp) bị xếp sau các việc thẩm mỹ như retrofit UI Admin (Entry 006, effort cao hơn, ít nghiêm trọng hơn), dễ khiến hội đồng hiểu sai về mức độ ưu tiên thực sự của nhóm. Contextualization: Báo cáo audit giữa kỳ cần thể hiện rõ tư duy ưu tiên rủi ro (risk-based prioritization), không chỉ là một nhật ký liệt kê phát hiện. Creative Synthesis: Tôi phân rã lại toàn bộ 6 phát hiện thành ma trận 2 chiều Mức độ nghiêm trọng (Cao/Trung bình/Thấp) x Effort khắc phục (Cao/Thấp), xếp thứ tự xử lý: (1) Bổ sung @PreAuthorize còn thiếu — Cao/Thấp, làm ngay; (2) Chặn race condition Voice-to-Form — Cao/Trung bình; (3) Hợp nhất Atomic Update Helper — Trung bình/Trung bình; (4) Retrofit Liquid Glass/AppIcon cho Admin — Thấp/Trung bình, có thể dời sang sprint sau. Decision: Trình bày roadmap khắc phục theo ma trận Mức độ nghiêm trọng x Effort thay vì liệt kê theo thứ tự phát hiện. | I84: Bảng ma trận ưu tiên AuditRoadmap.xlsx

Sheet 3. Hallucination Detection
A1: HALLUCINATION DETECTION LOG - ALL WEEKS (BẮT BUỘC)
A2: Tổng hợp toàn bộ các case hallucination đã phát hiện qua 11 tuần dự án. Mỗi project phải phát hiện ít nhất 3 case; tổng dự án đã phát hiện được nhiều hơn mức tối thiểu này.
A3: Week | B3: Entry # (from Sheet 2) | C3: Hallucination Type | D3: AI's Claim | E3: Reality Check | F3: How Detected | G3: Corrective Action
A4: Week 1 | B4: 008 | C4: Fabrication | D4: AI khuyên dùng thư viện kết nối và gọi đến 'Google DermAssist Open API' để triển khai tính năng phân tích hình ảnh soi da hoàn toàn miễn phí. | E4: Google DermAssist hiện tại là một dự án nghiên cứu nội bộ thuộc Google Health và hoàn toàn KHÔNG cung cấp Open API công khai cho bên thứ ba hoặc sinh viên lập trình. | F4: Tiến hành tra cứu tài liệu chính thức trên Google Cloud Console và trang chủ Google Health nhưng không tìm thấy bất kỳ tài liệu kỹ thuật nào về API này. | G4: Chuyển hướng sang phương án tự xây dựng model nhận diện nhỏ bằng Python cài đặt trên máy chủ hoặc sử dụng một mô hình Image Classification mã nguồn mở thay thế.
A5: Week 1 | B5: N/A | C5: Context Misunderstanding | D5: AI khẳng định giải pháp tốt nhất cho hệ thống quản lý phòng khám này là triển khai theo kiến trúc Microservices tách rời, quản lý bằng Docker và Kubernetes. | E5: Đây chỉ là một đồ án môn học SWP391 với quy mô nhóm 5 sinh viên thực hiện trong vài tháng. Kiến trúc Microservices là sự phức tạp hóa không cần thiết (Over-engineering), gây quá tải hạ tầng. | F5: Đánh giá và đối chiếu lại các giới hạn cốt lõi của dự án (Project Constraints) bao gồm thời gian bàn giao, nhân lực và yêu cầu thực tế của môn học. | G5: Bác bỏ đề xuất của AI, chốt thiết kế hệ thống theo kiến trúc Monolithic truyền thống kết hợp pattern MVC để dễ dàng kiểm soát, kiểm thử và deploy.
A6: Week 1 | B6: 009 | C6: Logic Error | D6: AI khẳng định thuật toán kiểm tra trùng lịch hẹn phòng khám chỉ cần thực hiện câu lệnh truy vấn SQL: `WHERE Appointment_Time = New_Time` là đủ. | E6: Thuật toán này bị sai logic toán học nghiêm trọng. Lịch hẹn bị giao nhau (overlap) xảy ra cả khi thời gian bắt đầu của ca mới nằm giữa khoảng thời gian khám của một ca cũ đã tồn tại. | F6: Vẽ trục thời gian trực quan ra giấy để chạy thử nghiệm các testcase biên (ví dụ: ca khám cũ kéo dài 30 phút bắt đầu từ 8:45 sẽ đè lên ca mới lúc 9:00). | G6: Tự viết lại logic kiểm tra toán học theo thuật toán Overlapping Intervals chuẩn xác: `A.start < B.end AND A.end > B.start`.
A7: Week 2 | B7: 003 | C7: Fabrication | D7: MySQL tích hợp sẵn bảng ảo bảo mật `PASSWORD_VALIDATOR_SECURE` tự động mã hóa mật khẩu khi INSERT vào DB mà không cần code mã hóa ở tầng Java. | E7: MySQL hoàn toàn KHÔNG có bảng ảo hay feature nào như vậy. Đây là thông tin do AI bịa đặt hoàn toàn. MySQL không tự mã hóa password — đây là trách nhiệm của tầng Application. | F7: Khi viết SQL gọi thử `SELECT * FROM PASSWORD_VALIDATOR_SECURE` trong MySQL Workbench → lỗi ngay: `Table 'db.PASSWORD_VALIDATOR_SECURE' doesn't exist`. Tra cứu MySQL 8.0 Official Docs không có feature này. | G7: Bác bỏ hoàn toàn, tự implement mã hóa đúng chuẩn tại tầng Java Backend dùng Spring Security BCryptPasswordEncoder. Không dựa vào bất kỳ feature DB nào không có trong official docs.
A8: Week 2 | B8: 010 | C8: Logic Error | D8: Code xác thực mật khẩu BCrypt bằng cách hash lại raw password rồi so sánh bằng toán tử `==`: `BCrypt.hashpw(rawPassword, storedHash) == storedHash`. | E8: BCrypt dùng Salt ngẫu nhiên — cùng password hash 2 lần cho ra 2 chuỗi hoàn toàn khác nhau. Toán tử `==` so sánh chuỗi ký tự (không phải semantic equality) sẽ luôn trả về false → tài khoản không bao giờ đăng nhập được dù mật khẩu đúng. | F8: Chạy Unit Test đăng nhập với mật khẩu đúng → hệ thống liên tục báo 'Sai mật khẩu'. Debug log phát hiện `BCrypt.hashpw()` trả về hash string khác với `storedHash` mỗi lần gọi. Tra cứu BCrypt documentation xác nhận cơ chế salt động. | G8: Xóa bỏ code lỗi, thay bằng `passwordEncoder.matches(rawPassword, encodedPassword)` của Spring Security. Method này hiểu salt động và verify đúng. Viết Unit Test confirm fix hoạt động.
A9: Week 2 | B9: N/A | C9: Outdated Info | D9: Hướng dẫn cấu hình Spring Security bằng cách kế thừa class `WebSecurityConfigurerAdapter` và override method `configure(HttpSecurity http)`. | E9: Class `WebSecurityConfigurerAdapter` đã bị đánh dấu @Deprecated từ Spring Security 5.7 và bị xóa hoàn toàn khỏi Spring Security 6.x (Spring Boot 3.x). Project đang dùng Spring Boot 3.x nên class này không tồn tại. | F9: Import `WebSecurityConfigurerAdapter` vào project Spring Boot 3.x → IDE báo lỗi đỏ ngay: 'Cannot resolve symbol WebSecurityConfigurerAdapter'. Tra cứu Spring Security 6 Migration Guide xác nhận class đã bị remove. | G9: Viết lại Security config theo cách mới của Spring Security 6: khai báo `@Bean SecurityFilterChain filterChain(HttpSecurity http)` thay vì extend adapter. Tra cứu Spring Security 6 official docs để implement đúng.
A10: Week 3 | B10: 001 | C10: Logic Error / Security | D10: AI hướng dẫn sinh mã OTP ngẫu nhiên bằng cách gọi hàm toán học cơ bản: `int otp = new Random().nextInt(999999);` và khẳng định giải pháp này an toàn tuyệt đối. | E10: Hàm `Random` trong Java sử dụng thuật toán giả ngẫu nhiên tuyến tính (PRNG) dựa trên mốc thời gian hệ thống, hoàn toàn có thể bị hacker dự đoán được chuỗi số tiếp theo. Ngoài ra, nếu số sinh ra nhỏ hơn 100000, chuỗi trả về chỉ có 4 hoặc 5 chữ số, phá vỡ định dạng 6 chữ số quy chuẩn. | F10: Khi chạy thử nghiệm sinh mã hàng loạt, hệ thống phát hiện có mã bị thiếu số (chỉ có 4 chữ số) và khi đọc tài liệu bảo mật OWASP thấy khuyến cáo nghiêm cấm dùng `Random` cho mã xác thực. | G10: Sửa lại mã nguồn, sử dụng lớp bảo mật mật mã chuyên dụng `SecureRandom` kết hợp chuỗi định dạng bọc số không ở đầu: `String.format("%06d", secureRandom.nextInt(1000000))`.
A11: Week 3 | B11: 004 | C11: Context Misunderstanding | D11: AI khẳng định giải pháp tốt nhất để cập nhật widget biểu đồ doanh thu theo thời gian thực trên Dashboard của Admin là mở kết nối WebSockets liên tục để lắng nghe thay đổi dữ liệu từng mili-giây. | E11: Dashboard của Admin quản lý vĩ mô chỉ cần số liệu cập nhật định kỳ hoặc khi tải lại trang. Việc bắt server duy trì một kết nối socket liên tục chỉ để đẩy số liệu doanh thu nhảy số theo mili-giây gây lãng phí tài nguyên CPU và băng thông mạng vô ích (Over-engineering). | F11: Phân tích hành vi tương tác thực tế của người dùng Admin: Admin không ngồi canh biểu đồ nhảy từng đồng theo giây, mà chỉ xem báo cáo báo cáo theo phiên làm việc. | G11: Bác bỏ đề xuất WebSockets của AI cho widget doanh thu, giữ nguyên cơ chế gọi API Restful thông thường kết hợp bộ nhớ đệm cache ngắn hạn (5 phút) tại server để tối ưu hiệu năng.
A12: Week 3 | B12: 002 | C12: Fabrication | D12: AI hướng dẫn cài đặt gói thư viện CSS bên thứ ba mang tên `tailwindcss-dashboard-presets-medical` để tự động render nhanh các widget chuyên dụng cho phòng khám da liễu. | E12: Trên thực tế hệ thống quản lý npm và kho tiện ích Tailwind CSS hoàn toàn KHÔNG tồn tại bất kỳ gói thư viện nào có tên là `tailwindcss-dashboard-presets-medical`. Đây là gói thư viện do AI tự tưởng tượng ra tên gọi. | F12: Khi gõ lệnh chạy cài đặt `npm install tailwindcss-dashboard-presets-medical`, hệ thống terminal lập tức trả về lỗi đỏ thông báo lỗi `ERR! 404 Not Found - Gói thư viện không tồn tại trên hệ thống đăng ký`. | G12: Xóa bỏ câu lệnh lỗi, tự tiến hành thiết kế và lập trình thủ công cấu trúc các widget giao diện y tế bằng các class core nền tảng chuẩn chỉnh có sẵn của Tailwind CSS.
A13: Week 4 | B13: 004 | C13: Fabrication | D13: ChatGPT khẳng định bộ thư viện Spring Data JPA cung cấp một annotation tích hợp sẵn là `@OptimisticLockRetry(maxAttempts = 3)` dùng để đính kèm lên phương thức của Service, giúp tự động thực hiện lại câu lệnh lưu dữ liệu bệnh án nếu xảy ra xung đột phiên bản (version conflict). | E13: Trong thực tế, bộ khung Spring Data JPA hay Hibernate hoàn toàn KHÔNG tồn tại bất kỳ annotation nào mang tên `@OptimisticLockRetry`. Đây là một annotation do AI tự bịa đặt ra tên gọi và cơ chế hoạt động. | F13: Khi tiến hành gõ annotation này vào mã nguồn Java trong môi trường IDE, trình biên dịch lập tức báo lỗi đỏ toàn bộ hệ thống vì không thể import được class thư viện này từ bất kỳ package nào. | G13: Xóa bỏ annotation hư cấu của AI, tự tiến hành viết một khía cạnh lập trình hướng khía cạnh (AOP Aspect) tùy chỉnh sử dụng `@Around` hoặc viết vòng lặp catch lỗi `ObjectOptimisticLockingFailureException` thủ công trong mã nguồn Java để tự thực hiện lại thao tác lưu dữ liệu (retry logic) tối đa 3 lần một cách chính thống.
A14: Week 4 | B14: 002 | C14: Logic Error | D14: Claude viết câu lệnh JPQL để lấy danh sách lịch làm việc và số lượng lịch hẹn hiện tại của Bác sĩ bằng phép kết nối chặt INNER JOIN giữa hai bảng Doctor và Appointment: `SELECT d FROM Doctor d INNER JOIN d.appointments a` và khẳng định câu lệnh này load đầy đủ thông tin màn hình bác sĩ. | E14: Câu lệnh JPQL này sai hoàn toàn về mặt logic toán học tập hợp. Phép kết nối INNER JOIN sẽ tự động loại bỏ (loại trừ hoàn toàn) những bác sĩ nào hiện tại chưa có bất kỳ lịch hẹn nào trong hệ thống, khiến họ bị biến mất hoàn toàn khỏi trang danh sách điều phối của phòng khám. | F14: Khi kiểm tra giao diện chạy thử nghiệm hệ thống vào đầu ngày (khi chưa có bệnh nhân nào đặt lịch khám), màn hình danh sách bác sĩ trống trơn không hiển thị bất kỳ một nhân sự y tế nào. | G14: Sửa lại logic truy vấn cơ sở dữ liệu, thay thế từ khóa `INNER JOIN` bằng phép kết nối mở rộng `LEFT JOIN FETCH` để đảm bảo hệ thống load đầy đủ toàn bộ danh sách bác sĩ y tế, bất kể họ đã có lịch hẹn hay chưa.
... A37: Week 11 | B37: 005 | C37: Logic Error | D37: Claude khẳng định chạy load test tuần tự với các request cách nhau 1 giây 'đảm bảo an toàn và dễ debug' là đủ để xác thực cơ chế chống tranh chấp dữ liệu đồng thời. | E37: Test tuần tự không bao giờ tạo ra tình huống nhiều luồng cùng chạm dữ liệu tại một thời điểm, do đó không thể phát hiện được race condition dù logic có lỗi hay không. | F37: Chạy thử kịch bản tuần tự trên một bản code cố tình chèn lỗi giả để kiểm chứng độ nhạy của test, kết quả test vẫn báo PASS dù lỗi giả đã được chèn vào, chứng minh test không có khả năng phát hiện tranh chấp thực sự. | G37: Thiết kế lại kịch bản bằng JMeter Thread Group 50 luồng đồng thời kết hợp Synchronizing Timer để đảm bảo request thực sự chạm database cùng lúc.
A38: TOTAL CASES | C38: =COUNTA(C4:C37) -> 34
A40: HALLUCINATION TYPES REFERENCE:
A41: Type | B41: Definition | C41: Example
A42: Fabrication | B42: AI tạo ra thông tin không tồn tại | C42: Fake papers, fake APIs, fake data
A43: Oversimplification | B43: AI bỏ qua edge cases, exceptions | C43: Code không handle trường hợp mảng/dữ liệu rỗng
A44: Logic Error | B44: AI đưa kết luận sai về 'best practice' | C44: Khẳng định một thuật toán luôn tối ưu trong mọi bối cảnh
A45: Outdated Info | B45: AI dùng thông tin cũ, không còn đúng | C45: Sử dụng cú pháp của các thư viện đã bị khai tử (deprecated)
A46: Context Misunderstanding | B46: AI không hiểu đúng bối cảnh | C46: Không nắm rõ các giới hạn tài nguyên và nghiệp vụ thực tế của dự án

Sheet 4. Self-Assessment Checklist
A1: SELF-ASSESSMENT CHECKLIST - ALL WEEKS (Trước khi nộp)
A2: Tổng hợp kiểm tra chất lượng cho toàn bộ 81 core prompts qua 11 tuần trước khi nộp báo cáo cuối kỳ.
A4: A. KIỂM TRA CHẤT LƯỢNG TOÀN DỰ ÁN (Yêu cầu Pass >=4/5 mỗi entry)
A5: # | B5: Tiêu chí bảo đảm chất lượng | C5: Pass? | D5: Note
A6: 1 | B6: Prompt này ảnh hưởng đến quyết định quan trọng trong project? | C6: ☑ | D6: Đã kiểm soát kỹ 81 quyết định kỹ thuật xuyên suốt 11 tuần
A7: 2 | B7: Nếu không có prompt này, project có thay đổi về architecture/design? | C7: ☑ | D7: Ảnh hưởng trực tiếp kiến trúc DB, bảo mật, luồng nghiệp vụ và các tính năng AI
A8: 3 | B8: Tôi có thể giải thích lý do chọn/không chọn gợi ý của AI? | C8: ☑ | D8: Mỗi entry đều có đủ 4 phần Critical Thinking/Contextualization/Creative Synthesis/Decision
A9: 4 | B9: Có minh chứng cụ thể (code, metrics, comparison)? | C9: ☑ | D9: 81/81 entries đều chỉ định rõ tệp mã nguồn/minh chứng đính kèm
A10: 5 | B10: Prompt này phản ánh tư duy phản biện, không chỉ copy AI? | C10: ☑ | D10: Chứng minh xuyên suốt qua việc phản biện và sửa lại đề xuất ban đầu của AI ở từng tuần
A12: B. KIỂM TRA TỔNG THỂ TOÀN BỘ DỰ ÁN (11 TUẦN)
A13: # | B13: Tiêu chí tổng thể hệ thống | C13: Pass? | D13: Current Value (Toàn dự án)
A14: 1 | B14: Số lượng entries nằm trong range (min-max) mỗi tuần? | C14: ☑ | D14: ="81 entries / "&'1. Overview & Per-Week Summary'!C11&" prompts (Tỷ lệ "&TEXT('1. Overview & Per-Week Summary'!C13,"0.0%")&")" -> 81 entries / 585 prompts (Tỷ lệ 13.8%)
A15: 2 | B15: Mỗi DTC component có ít nhất 1 core prompt mỗi tuần? | C15: ☑ | D15: ="D("&'1. Overview & Per-Week Summary'!B40&"), P("&'1. Overview & Per-Week Summary'!B41&"), A("&'1. Overview & Per-Week Summary'!B42&"), Alg("&'1. Overview & Per-Week Summary'!B43&") - đầy đủ mặt mỗi tuần" -> D(24), P(24), A(18), Alg(15) - đầy đủ mặt mỗi tuần
A16: 3 | B16: Đã phát hiện >= số lượng hallucination yêu cầu mỗi tuần? | C16: ☑ | D16: ="Tổng "&'3. Hallucination Detection'!C38&" case hallucination đã kê khai và khắc phục qua 11 tuần" -> Tổng 34 case hallucination đã kê khai và khắc phục qua 11 tuần
A17: 4 | B17: Mỗi entry đều có Human Delta đầy đủ (4 câu hỏi)? | C17: ☑ | D17: 100% (81/81) các dòng đều điền đủ 4 ý gốc
A18: 5 | B18: Có evidence cho >=70% entries? | C18: ☑ | D18: 100% (81/81) entries đều chỉ định bằng chứng
A20: C. CHUẨN BỊ CHO ORAL VIVAS (Q&A) - TOÀN BỘ 11 TUẦN
A21: Giảng viên có thể hỏi ngẫu nhiên bất kỳ entry nào trong 11 tuần. Tự hỏi bản thân:
A22: Week | B22: Entry # | C22: Tôi có thể giải thích tại sao chọn approach này? | D22: Tôi có nhớ AI response? | E22: Tôi có evidence?
A23: Week 1 | B23: 001
A24: Week 1 | B24: 002
A25: Week 1 | B25: 003
A26: Week 2 | B26: 001 | C26: Có — Giải thích tại sao tách SMTP OTP thành Phase B, dev dùng OTP trong JSON response để không block sprint. | D26: Gemini: 7 bước đầy đủ có SMTP ngay từ đầu. | E26: Sơ đồ luồng đăng ký; API list
A27: Week 2 | B27: 002 | C27: Có — Giải thích gộp component lại tránh Prop Drilling khi chưa có Redux. | D27: Claude: 5 leaf component tự fetch data độc lập. | E27: Sơ đồ UI Component
A28: Week 2 | B28: 003 | C28: Có — Giải thích gộp password_hash vào Account table đủ bảo mật nếu hash đúng cách. | D28: Gemini: Tách bảng User_Passwords riêng. | E28: SQL script Account table
A29: Week 2 | B29: 004 | C29: Có — Giải thích Structured Audit Log với cột tường minh query nhanh hơn JSON blob. | D29: ChatGPT: Lưu JSON trong 1 cột TEXT. | E29: ERD System_Audits; Index DDL
A30: Week 2 | B30: 005 | C30: Có — Giải thích tách 2 trang riêng + Inline Validation tốt hơn Sliding Card cho mobile. | D30: Claude: Sliding Card animation + Pop-up alert. | E30: Figma Wireframe; LoginPage.jsx
A31: Week 3 | B31: 1 | C31: Tại sao em không chọn giải pháp WebSockets để cập nhật widget doanh thu của Admin giống như AI đề xuất ban đầu? | D31: Trả lời dựa vào tính thực tế: Dashboard Admin xem báo cáo vĩ mô, không cần nhảy số theo mili-giây. Dùng WebSockets gây lãng phí CPU/băng thông mạng vô ích. | E31: Hiệu năng & Tối ưu hóa hạ tầng (Restful + Cache 5 phút thay vì duy trì Socket liên tục).
A32: Week 3 | B32: 2 | C32: Cơ chế kiểm soát thời gian hết hạn (`expiry_time`) và số lần nhập sai (`failed_attempts`) của mã OTP được em triển khai như thế nào ở code Backend? | D32: Giải thích luồng: Lưu mã kèm timestamp trong DB. Mỗi lần user nhập sai thì tăng biến đếm lên 1. Nếu đếm > 5 hoặc hiện tại > expiry_time thì hủy phiên xác thực. | E32: Bảo mật hệ thống phòng chống tấn công dò mã tự động (Brute-Force Attack Protection).
A33: Week 3 | B33: 3 | C33: Em giải thích thế nào về việc bác bỏ giải pháp lưu thông tin Dashboard độc lập của AI để chuyển sang mô hình UI Shell Component chung? | D33: Trả lời dựa trên nguyên lý quản lý mã nguồn: Tránh trùng lặp code (DRY principle). Gom Sidebar/Header về một Layout chung, chỉ render động các menu dựa trên mảng cấu hình role. | E33: Kiến trúc Frontend mô-đun hóa, tăng khả năng bảo trì và nâng cấp giao diện.
A34: Week 3 | B34: 4 | C34: Làm thế nào để bộ lọc Route Guard ở Next.js Middleware chặn được hacker xâm nhập trang Dashboard Admin, thay vì dùng `useEffect` ở Client-side? | D34: Giải thích cơ chế đánh chặn: Middleware chạy ở môi trường Edge/Server trước khi bất kỳ file HTML/JS nào được gửi về trình duyệt. Nếu role không khớp, server sẽ redirect ngay lập tức. | E34: Bảo mật Server-side Authentication, triệt tiêu khả năng bypass bảo mật bằng cách can thiệp JavaScript tại trình duyệt.
A35: Week 4 | B35: 1 | C35: Tại sao em lại chọn mô hình Kế thừa bảng liên kết (Joined Table Inheritance) thay vì tách biệt bảng độc lập cho LabTest và Procedure? | D35: Có | E35: Có
A36: Week 4 | B36: 2 | C36: Làm thế nào phương thức `JOIN FETCH` trong câu lệnh JPQL của em giải quyết được vấn đề hiệu năng N+1 Select Problem khi bác sĩ mở bệnh án? | D36: Có | E36: Có
A37: Week 4 | B37: 3 | C37: Tại sao em bác bỏ đề xuất dùng Khóa bi quan (Pessimistic Lock) của AI để chuyển sang Khóa lạc quan (Optimistic Lock) cho thực thể bệnh án? | D37: Có | E37: Có
... A86: Week 11 | B86: 007 | C86: Có — Tại sao em trình bày roadmap khắc phục theo ma trận Mức độ nghiêm trọng x Effort thay vì liệt kê theo thứ tự phát hiện như Claude gợi ý? | D86: Claude: Liệt kê phát hiện theo đúng thứ tự Entry 001-006, không phân mức độ ưu tiên. Tôi xếp lại theo ma trận nghiêm trọng/effort để thể hiện đúng tư duy ưu tiên rủi ro trong báo cáo audit. | E86: File: `AuditRoadmap.xlsx`
